runic/cli.py
runic/memory.py
runic/templates/orchestrator.md
runic/templates/specialist.md
runic/templates/core/commands.md
runic/templates/core/identity.md
runic/templates/core/memory-structure.md
runic/templates/core/memory-updates.md
runic/templates/core/rules.md
runic/templates/memory/active-context.md
runic/templates/memory/product-context.md
runic/templates/memory/progress.md
runic/templates/memory/project-brief.md
runic/templates/memory/system-patterns.md
runic/templates/memory/tech-context.md
runic/templates/memory/tracks/track-management.md
runic-1.0.0.dist-info/METADATA
runic-1.0.0.dist-info/WHEEL
runic-1.0.0.dist-info/entry_points.txt
runic-1.0.0.dist-info/RECORD
