Metadata-Version: 2.4
Name: runic
Version: 1.0.0
Summary: A lightweight framework for parallel development with multiple AI agents
Project-URL: Homepage, https://github.com/livingstonlarus/runic
Project-URL: Bug Tracker, https://github.com/livingstonlarus/runic/issues
Author-email: Livingston Larus <contact@livingstonlarus.com>
Classifier: License :: OSI Approved :: MIT License
Classifier: Operating System :: OS Independent
Classifier: Programming Language :: Python :: 3
Requires-Python: >=3.8
Requires-Dist: click>=8.1.3
